metatrace/__init__.py
metatrace/api/__init__.py
metatrace/cli/__init__.py
metatrace/cli/__main__.py
metatrace/cli/data/__init__.py
metatrace/cli/metadata/__init__.py
metatrace/cli/metadata/asn.py
metatrace/cli/metadata/base.py
metatrace/cli/metadata/geo.py
metatrace/cli/metadata/ixp.py
metatrace/lib/__init__.py
metatrace/lib/clickhouse.py
metatrace/lib/credentials.py
metatrace/lib/data/__init__.py
metatrace/lib/logger.py
metatrace/lib/metadata/__init__.py
metatrace/lib/metadata/asn.py
metatrace/lib/metadata/base.py
metatrace/lib/metadata/geo.py
metatrace/lib/metadata/ixp.py
metatrace/lib/naming.py
metatrace/lib/sources/__init__.py
metatrace/lib/sources/ark.py
metatrace/lib/sources/collectors.py
metatrace/lib/sources/peeringdb.py
metatrace/lib/utilities.py
metatrace/static/css/bootstrap.min.css
metatrace/static/css/bootstrap.min.css.map
metatrace/static/css/main.css
metatrace/static/fonts/bootstrap-icons-1.8.3/123.svg
metatrace/static/fonts/bootstrap-icons-1.8.3/activity.svg
metatrace/static/fonts/bootstrap-icons-1.8.3/alarm-fill.svg
metatrace/static/fonts/bootstrap-icons-1.8.3/alarm.svg
metatrace/static/fonts/bootstrap-icons-1.8.3/align-bottom.svg
metatrace/static/fonts/bootstrap-icons-1.8.3/align-center.svg
metatrace/static/fonts/bootstrap-icons-1.8.3/align-end.svg
metatrace/static/fonts/bootstrap-icons-1.8.3/align-middle.svg
metatrace/static/fonts/bootstrap-icons-1.8.3/align-start.svg
metatrace/static/fonts/bootstrap-icons-1.8.3/align-top.svg
metatrace/static/fonts/bootstrap-icons-1.8.3/alt.svg
metatrace/static/fonts/bootstrap-icons-1.8.3/app-indicator.svg
metatrace/static/fonts/bootstrap-icons-1.8.3/app.svg
metatrace/static/fonts/bootstrap-icons-1.8.3/apple.svg
metatrace/static/fonts/bootstrap-icons-1.8.3/archive-fill.svg
metatrace/static/fonts/bootstrap-icons-1.8.3/archive.svg
metatrace/static/fonts/bootstrap-icons-1.8.3/arrow-90deg-down.svg
metatrace/static/fonts/bootstrap-icons-1.8.3/arrow-90deg-left.svg
metatrace-0.1.0.dist-info/LICENSE
metatrace-0.1.0.dist-info/METADATA
metatrace-0.1.0.dist-info/WHEEL
metatrace-0.1.0.dist-info/entry_points.txt
metatrace-0.1.0.dist-info/RECORD
