Metadata-Version: 2.1
Name: metatrace
Version: 0.1.0
Summary: 
Home-page: https://github.com/dioptra-io/metatrace
License: MIT
Author: Maxime Mouchet
Author-email: maxime.mouchet@lip6.fr
Requires-Python: >=3.10,<4.0
Classifier: License :: OSI Approved :: MIT License
Classifier: Programming Language :: Python :: 3
Classifier: Programming Language :: Python :: 3.10
Classifier: Programming Language :: Python :: 3.11
Classifier: Programming Language :: Python :: 3.12
Requires-Dist: Babel (>=2.10.1,<3.0.0)
Requires-Dist: DateTimeRange (>=1.2.0,<2.0.0)
Requires-Dist: Jinja2 (>=3.1.2,<4.0.0)
Requires-Dist: Pint (>=0.19.2,<0.20.0)
Requires-Dist: arel (>=0.2.0,<0.3.0)
Requires-Dist: beautifulsoup4 (>=4.11.1,<5.0.0)
Requires-Dist: fastapi (>=0.80.0,<0.81.0)
Requires-Dist: more-itertools (>=8.14.0,<9.0.0)
Requires-Dist: pandas (>=1.4.3,<2.0.0)
Requires-Dist: pyasn (>=1.6.1,<2.0.0)
Requires-Dist: pych-client (>=0.3.1,<0.4.0)
Requires-Dist: rich (>=12.5.1,<13.0.0)
Requires-Dist: typer (>=0.6.1,<0.7.0)
Requires-Dist: uvicorn[standard] (>=0.18.2,<0.19.0)
